{
 "nombre": "Conciencia Histórica (área)",
 "generacion": "2025-2028",
 "componente": "fundamental",
 "url": "https://dgb.sep.gob.mx/storage/recursos/2025/09/H4sa0TNb65-MCC_CONCIENCIA-HISTORICA.pdf",
 "slug": "conciencia-historica-area--2025-2028",
 "proposito": ", constituyen \nel conjunto de capacidades, saberes y procesos significativos y contextualizados \nque deben vincularse con los intereses, necesidades y realidades del estudiantado, \npromoviéndose así una educación transformadora.2. Metas educativas, propósitos y \n contenidos formativos de asignatura\n| Conciencia Histórica\n14En Conciencia Histórica I. Coordenadas de la Historia se busca que el estudiantado \naprenda los diferentes conceptos y categorías para el análisis del pasado, los que le \npermitirán formular problemas o preguntas de investigación, sujetas a resolverse \nmediante las herramientas que proporciona la disciplina (ver tabla 1).2.1. Conciencia Histórica I\n Coordenadas de la Historia\nTabla 1. Propósitos y contenidos formativos de Conciencia Histórica I. Coorde-\nnadas de la Historia\nNombre de la asignatura \nConciencia Histórica I\nCoordenadas de la HistoriaMeta educativa\nFormule problemas históricos a \npartir del análisis de los conceptos y \ncategorías fundamentales de la His-\ntoria como disciplina, para fortalecer \nuna mirada crítica, situada y reflexiva \nsobre el pasado, presente, y futuro \ncomo parte fundamental de la con-\nciencia histórica.Cuarto semestre\nHoras/semana:",
 "progresiones": [],
 "metas_aprendizaje": [],
 "contenidos": [
  "de asignatura 13\n1. Presentación 9\n\n| Conciencia Histórica\n8\n\nConciencia Histórica | 9\n9El Modelo 2025 del Marco Curricular Común de la Educación Media Superior (MC-\nCEMS) es el resultado de un proceso de diagnóstico y análisis en el que participa-\nron integrantes de la comunidad educativa a nivel nacional: estudiantes, personal \ndocente y autoridades. En este ejercicio, se identificaron desafíos en la práctica \neducativa y, para dar respuesta a este panorama, los nuevos programas de asig-\nnatura del MCCEMS parten de un enfoque pedagógico crítico que dinamiza los \nprocesos de aprendizaje y enseñanza. \nLos programas del MCCEMS tienen como finalidad orientar al personal docente \npara que tome decisiones de manera autónoma y contextualizada, favoreciendo \nla diversidad de enfoques, necesidades y realidades de la comunidad estudiantil. \nAsimismo, permiten a la comunidad docente diseñar planeaciones con una acti-\ntud reflexiva, colaborativa y crítica, desde la creatividad y la autonomía curricular .\nEn este documento se pueden consultar los propósitos y los contenidos forma-\ntivos de cada semestre de la asignatura Conciencia Histórica, así como algunas \norientaciones didácticas y criterios para la evaluación del aprendizaje.\nLa asignatura Conciencia Histórica surge como una respuesta alternativa a la con-\ncepción tradicional del aprendizaje en el aula, donde estudiar historia era perci-\nbido únicamente como la transmisión de conocimientos factuales sobre eventos, \nfechas, personaj"
 ],
 "calidad_extraccion": "PARCIAL",
 "extraido_con": "extraer_progresiones.py v1"
}